ai_core_sdk/__init__.py
ai_core_sdk/ai_core_v2_client.py
ai_core_sdk/cli.py
ai_core_sdk/credentials.py
ai_core_sdk/exception.py
ai_core_sdk/helpers/__init__.py
ai_core_sdk/helpers/constants.py
ai_core_sdk/helpers/logging.py
ai_core_sdk/models/__init__.py
ai_core_sdk/models/application.py
ai_core_sdk/models/application_query_response.py
ai_core_sdk/models/application_resource_sync_status.py
ai_core_sdk/models/application_source.py
ai_core_sdk/models/application_status.py
ai_core_sdk/models/base_models.py
ai_core_sdk/models/docker_registry_secret.py
ai_core_sdk/models/docker_registry_secret_query_response.py
ai_core_sdk/models/kpi.py
ai_core_sdk/models/object_store_secret.py
ai_core_sdk/models/object_store_secret_query_response.py
ai_core_sdk/models/repository.py
ai_core_sdk/models/repository_query_response.py
ai_core_sdk/models/repository_status.py
ai_core_sdk/models/resource_group.py
ai_core_sdk/models/resource_group_query_response.py
ai_core_sdk/models/resource_group_status.py
ai_core_sdk/models/secret.py
ai_core_sdk/models/secret_query_response.py
ai_core_sdk/resource_clients/__init__.py
ai_core_sdk/resource_clients/applications_client.py
ai_core_sdk/resource_clients/docker_registry_secrets_client.py
ai_core_sdk/resource_clients/internal_rest_client.py
ai_core_sdk/resource_clients/kpi_client.py
ai_core_sdk/resource_clients/metrics_client.py
ai_core_sdk/resource_clients/object_store_secrets_client.py
ai_core_sdk/resource_clients/repositories_client.py
ai_core_sdk/resource_clients/secrets_client.py
ai_core_sdk/tracking/__init__.py
ai_core_sdk/tracking/tracking.py
sap_ai_sdk_core-3.1.2.data/data/docs/ai_core_sdk.ai_core_v2_client.html
sap_ai_sdk_core-3.1.2.data/data/docs/ai_core_sdk.cli.html
sap_ai_sdk_core-3.1.2.data/data/docs/ai_core_sdk.credentials.html
sap_ai_sdk_core-3.1.2.data/data/docs/ai_core_sdk.exception.html
sap_ai_sdk_core-3.1.2.data/data/docs/ai_core_sdk.helpers.constants.html
sap_ai_sdk_core-3.1.2.data/data/docs/ai_core_sdk.helpers.html
sap_ai_sdk_core-3.1.2.dist-info/LICENSE
sap_ai_sdk_core-3.1.2.dist-info/METADATA
sap_ai_sdk_core-3.1.2.dist-info/WHEEL
sap_ai_sdk_core-3.1.2.dist-info/entry_points.txt
sap_ai_sdk_core-3.1.2.dist-info/top_level.txt
sap_ai_sdk_core-3.1.2.dist-info/RECORD
